<?xml version="1.0" encoding="UTF-8"?>
<!DOCTYPE mapper PUBLIC "-//mybatis.org//DTD Mapper 3.0//EN" "http://mybatis.org/dtd/mybatis-3-mapper.dtd">
<mapper namespace="com.pig4cloud.pig.eh.mapper.EhApplyMapper">
	<select id="selectAdminApplyBaseList" resultType="com.pig4cloud.pig.eh.vo.AdminApplyPageVO">
		SELECT
			a.id,
			a.subject AS title,
			a.meeting_nature AS meetingNature,
			a.visitor_company AS unit,
			a.industry,
			a.district,
			a.applicant,
			a.phone,
			a.applicant_dept AS dept,
			a.start_time AS startTime,
			a.end_time AS endTime,
			a.top_leader_title AS leader,
			a.visitor_count AS headCount,
			a.customer_count AS customerCount,
			a.internal_count AS internalCount,
			a.agenda,
			a.status,
			a.create_time AS created,
			v.actual_visit_count AS actualHeadCount,
			v.actual_visit_time AS actualVisitTime,
			v.opportunity_code AS opportunityCode,
			v.return_signer AS returnSigner,
			v.return_time AS returnTime,
			v.status AS visitStatus,
			COALESCE(p.photo_count, 0) AS photoCount
		FROM eh_apply a
		LEFT JOIN eh_visit_record v ON v.apply_id = a.id AND v.del_flag = '0'
		LEFT JOIN (
			SELECT
				COALESCE(p.apply_id, vr.apply_id) AS apply_id,
				COUNT(*) AS photo_count
			FROM eh_visit_photo p
			LEFT JOIN eh_visit_record vr ON vr.id = p.visit_id AND vr.del_flag = '0'
			WHERE p.del_flag = '0'
			GROUP BY COALESCE(p.apply_id, vr.apply_id)
		) p ON p.apply_id = a.id
		WHERE a.del_flag = '0'
		<if test="status != null and status != ''">
			AND a.status = #{status}
		</if>
		ORDER BY a.create_time DESC
	</select>
	<select id="selectAdminApplyBaseListIn" resultType="com.pig4cloud.pig.eh.vo.AdminApplyPageVO">
		SELECT
			a.id,
			a.subject AS title,
			a.meeting_nature AS meetingNature,
			a.visitor_company AS unit,
			a.industry,
			a.district,
			a.applicant,
			a.phone,
			a.applicant_dept AS dept,
			a.start_time AS startTime,
			a.end_time AS endTime,
			a.top_leader_title AS leader,
			a.visitor_count AS headCount,
			a.customer_count AS customerCount,
			a.internal_count AS internalCount,
			a.agenda,
			a.status,
			a.create_time AS created,
			v.actual_visit_count AS actualHeadCount,
			v.actual_visit_time AS actualVisitTime,
			v.opportunity_code AS opportunityCode,
			v.return_signer AS returnSigner,
			v.return_time AS returnTime,
			v.status AS visitStatus,
			COALESCE(p.photo_count, 0) AS photoCount
		FROM eh_apply a
		LEFT JOIN eh_visit_record v ON v.apply_id = a.id AND v.del_flag = '0'
		LEFT JOIN (
			SELECT
				COALESCE(p.apply_id, vr.apply_id) AS apply_id,
				COUNT(*) AS photo_count
			FROM eh_visit_photo p
			LEFT JOIN eh_visit_record vr ON vr.id = p.visit_id AND vr.del_flag = '0'
			WHERE p.del_flag = '0'
			GROUP BY COALESCE(p.apply_id, vr.apply_id)
		) p ON p.apply_id = a.id
		WHERE a.del_flag = '0'
		AND a.status IN
		<foreach collection="statuses" item="s" open="(" separator="," close=")">#{s}</foreach>
		ORDER BY a.create_time DESC
	</select>
</mapper>
